ikabot/__init__.py
ikabot/__main__.py
ikabot/command_line.py
ikabot/config.py
ikabot/function/__init__.py
ikabot/function/activateMiracle.py
ikabot/function/activateShrine.py
ikabot/function/alertAttacks.py
ikabot/function/alertLowWine.py
ikabot/function/attackBarbarians.py
ikabot/function/autoBarbarians.py
ikabot/function/autoPirate.py
ikabot/function/buyResources.py
ikabot/function/checkForUpdate.py
ikabot/function/consolidateResources.py
ikabot/function/constructBuilding.py
ikabot/function/constructionList.py
ikabot/function/decaptchaConf.py
ikabot/function/distributeResources.py
ikabot/function/donate.py
ikabot/function/donationBot.py
ikabot/function/dumpWorld.py
ikabot/function/getStatus.py
ikabot/function/importExportCookie.py
ikabot/function/investigate.py
ikabot/function/killTasks.py
ikabot/function/loadCustomModule.py
ikabot/function/loginDaily.py
ikabot/function/logs.py
ikabot/function/modifyProduction.py
ikabot/function/proxyConf.py
ikabot/function/searchForIslandSpaces.py
ikabot/function/sellResources.py
ikabot/function/sendResources.py
ikabot/function/shipMovements.py
ikabot/function/stationArmy.py
ikabot/function/testTelegramBot.py
ikabot/function/trainArmy.py
ikabot/function/update.py
ikabot/function/vacationMode.py
ikabot/function/webServer.py
ikabot/helpers/__init__.py
ikabot/helpers/aesCipher.py
ikabot/helpers/apiComm.py
ikabot/helpers/botComm.py
ikabot/helpers/dns.py
ikabot/helpers/getJson.py
ikabot/helpers/gui.py
ikabot/helpers/logging.py
ikabot/helpers/market.py
ikabot/helpers/naval.py
ikabot/helpers/pedirInfo.py
ikabot/helpers/planRoutes.py
ikabot/helpers/process.py
ikabot/helpers/resources.py
ikabot/helpers/signals.py
ikabot/helpers/varios.py
ikabot/locale/es/LC_MESSAGES/activateMiracle.po
ikabot/locale/es/LC_MESSAGES/aesCipher.po
ikabot/locale/es/LC_MESSAGES/alertAttacks.po
ikabot/locale/es/LC_MESSAGES/alertLowWine.po
ikabot/locale/es/LC_MESSAGES/botComm.po
ikabot/locale/es/LC_MESSAGES/buyResources.po
ikabot-7.2.5.dist-info/licenses/LICENSE
ikabot-7.2.5.dist-info/METADATA
ikabot-7.2.5.dist-info/WHEEL
ikabot-7.2.5.dist-info/entry_points.txt
ikabot-7.2.5.dist-info/top_level.txt
ikabot-7.2.5.dist-info/RECORD
