Metadata-Version: 2.4
Name: ikabot
Version: 7.2.5
Home-page: https://github.com/Ikabot-Collective/ikabot
Author: physics-sp
Author-email: physics-sp@protonmail.com
License: MIT
Classifier: Programming Language :: Python :: 3
Classifier: License :: OSI Approved :: MIT License
License-File: LICENSE
Requires-Dist: requests
Requires-Dist: requests[socks]
Requires-Dist: cryptography
Requires-Dist: psutil
Provides-Extra: webserver
Requires-Dist: flask; extra == "webserver"
Dynamic: author
Dynamic: author-email
Dynamic: classifier
Dynamic: description
Dynamic: description-content-type
Dynamic: home-page
Dynamic: license
Dynamic: license-file
Dynamic: provides-extra
Dynamic: requires-dist
